CTkGradient/__init__.py
CTkGradient/gradient.py
CTkGradient/gradient_frame.py
CTkGradient-0.3.2.dist-info/LICENSE
CTkGradient-0.3.2.dist-info/METADATA
CTkGradient-0.3.2.dist-info/WHEEL
CTkGradient-0.3.2.dist-info/top_level.txt
CTkGradient-0.3.2.dist-info/RECORD
