Metadata-Version: 2.1
Name: CTkGradient
Version: 0.3.2
Summary: Create a gradient frame for customtkinter.
Home-page: https://github.com/TrollSkull/CTkGradient
Author: TrollSkull
Author-email: <trollskull.contact@gmail.com>
License: MIT
Keywords: python,tkinter,customtkinter,gradient
Classifier: Development Status :: 1 - Planning
Classifier: Intended Audience :: Developers
Classifier: Programming Language :: Python :: 3
Classifier: Operating System :: Unix
Classifier: Operating System :: MacOS :: MacOS X
Classifier: Operating System :: Microsoft :: Windows
License-File: LICENSE
Requires-Dist: customtkinter
